my/entry.py
web/app.py
web/static/style.css
web/templates/index.html
web_minio_upload-0.1.24.dist-info/METADATA
web_minio_upload-0.1.24.dist-info/WHEEL
web_minio_upload-0.1.24.dist-info/entry_points.txt
web_minio_upload-0.1.24.dist-info/top_level.txt
web_minio_upload-0.1.24.dist-info/RECORD
