Metadata-Version: 2.2
Name: web-minio-upload
Version: 0.1.24
Summary: Upload files to MinIO using a web interface.
Requires-Python: >=3.10
Requires-Dist: flask>=3.1.0
Requires-Dist: minio>=7.2.15
Requires-Dist: python-dotenv>=1.0.1
